[
  {
    "phrase": "do up",
    "meaning_vi": "sửa sang, tân trang lại",
    "type": "phrasal_verb",
    "examples": [
      {
        "en": "We're planning to do up the kitchen next month.",
        "vi": "Chúng tôi dự định sửa sang lại bếp vào tháng sau."
      },
      {
        "en": "They did up the old house and sold it for a profit.",
        "vi": "Họ tân trang lại ngôi nhà cũ và bán nó có lời."
      }
    ],
    "collocations": [
      "do up a room",
      "do up a house",
      "do up a flat"
    ],
    "response": "",
    "example_dialogue": [
      {
        "speaker": "A",
        "text": "Are you going to do up the bathroom?"
      },
      {
        "speaker": "B",
        "text": "Yes, we're planning to do it up next spring."
      }
    ]
  },
  {
    "phrase": "move in",
    "meaning_vi": "chuyển đến ở",
    "type": "phrasal_verb",
    "examples": [
      {
        "en": "We moved in last weekend.",
        "vi": "Chúng tôi chuyển đến ở cuối tuần trước."
      },
      {
        "en": "When are you moving in?",
        "vi": "Khi nào bạn chuyển đến ở?"
      }
    ],
    "collocations": [
      "move in together",
      "move in with someone",
      "move in date"
    ],
    "response": "",
    "example_dialogue": [
      {
        "speaker": "A",
        "text": "Have you moved into your new place yet?"
      },
      {
        "speaker": "B",
        "text": "Yes, we moved in yesterday."
      }
    ]
  },
  {
    "phrase": "move out",
    "meaning_vi": "chuyển ra ngoài",
    "type": "phrasal_verb",
    "examples": [
      {
        "en": "She moved out of her parents' house last year.",
        "vi": "Cô ấy chuyển ra khỏi nhà bố mẹ năm ngoái."
      },
      {
        "en": "We need to move out by the end of the month.",
        "vi": "Chúng tôi cần chuyển ra trước cuối tháng."
      }
    ],
    "collocations": [
      "move out of the house",
      "move out date",
      "move out on one's own"
    ],
    "response": "",
    "example_dialogue": [
      {
        "speaker": "A",
        "text": "When are you moving out?"
      },
      {
        "speaker": "B",
        "text": "I'm moving out next Saturday."
      }
    ]
  },
  {
    "phrase": "set up home",
    "meaning_vi": "lập gia đình, dọn về ở chung",
    "type": "collocation",
    "examples": [
      {
        "en": "They decided to set up home together after getting married.",
        "vi": "Họ quyết định lập gia đình sau khi kết hôn."
      },
      {
        "en": "It takes time to set up home in a new country.",
        "vi": "Cần thời gian để ổn định cuộc sống ở một đất nước mới."
      }
    ],
    "collocations": [
      "set up home together",
      "set up home abroad",
      "set up home with someone"
    ],
    "response": "",
    "example_dialogue": [
      {
        "speaker": "A",
        "text": "Are you planning to set up home soon?"
      },
      {
        "speaker": "B",
        "text": "Yes, we want to buy a place and settle down."
      }
    ]
  },
  {
    "phrase": "home away from home",
    "meaning_vi": "nơi thân thuộc như ở nhà",
    "type": "expression",
    "examples": [
      {
        "en": "This hotel is a home away from home for me.",
        "vi": "Khách sạn này là nơi thân thuộc như ở nhà đối với tôi."
      },
      {
        "en": "She considers my house a home away from home.",
        "vi": "Cô ấy coi nhà tôi như nhà mình."
      }
    ],
    "collocations": [
      "feel like a home away from home",
      "a true home away from home"
    ],
    "response": "",
    "example_dialogue": [
      {
        "speaker": "A",
        "text": "I love staying at your place."
      },
      {
        "speaker": "B",
        "text": "Thanks, I want it to be a home away from home for you."
      }
    ]
  },
  {
    "phrase": "make yourself at home",
    "meaning_vi": "cứ tự nhiên như ở nhà",
    "type": "expression",
    "examples": [
      {
        "en": "Please come in and make yourself at home.",
        "vi": "Mời vào và cứ tự nhiên như ở nhà."
      },
      {
        "en": "He made himself at home on the sofa.",
        "vi": "Anh ấy ngồi trên ghế sofa thoải mái như ở nhà."
      }
    ],
    "collocations": [
      "make yourself at home",
      "feel at home",
      "be at home"
    ],
    "response": "Thanks, I will.",
    "example_dialogue": [
      {
        "speaker": "A",
        "text": "Make yourself at home while I get the drinks."
      },
      {
        "speaker": "B",
        "text": "Thanks, I will."
      }
    ]
  },
  {
    "phrase": "home improvement",
    "meaning_vi": "cải tạo nhà cửa",
    "type": "collocation",
    "examples": [
      {
        "en": "We spent a lot on home improvement this year.",
        "vi": "Năm nay chúng tôi chi nhiều cho việc cải tạo nhà."
      },
      {
        "en": "Home improvement projects can increase property value.",
        "vi": "Các dự án cải tạo nhà có thể tăng giá trị bất động sản."
      }
    ],
    "collocations": [
      "home improvement project",
      "home improvement store",
      "DIY home improvement"
    ],
    "response": "",
    "example_dialogue": [
      {
        "speaker": "A",
        "text": "What are you doing this weekend?"
      },
      {
        "speaker": "B",
        "text": "Some home improvement work in the garden."
      }
    ]
  },
  {
    "phrase": "living space",
    "meaning_vi": "không gian sống",
    "type": "collocation",
    "examples": [
      {
        "en": "The apartment has a large living space.",
        "vi": "Căn hộ có không gian sống rộng."
      },
      {
        "en": "We need to maximize our living space.",
        "vi": "Chúng tôi cần tối đa hóa không gian sống."
      }
    ],
    "collocations": [
      "open living space",
      "living space design",
      "expand living space"
    ],
    "response": "",
    "example_dialogue": [
      {
        "speaker": "A",
        "text": "How do you like the new flat?"
      },
      {
        "speaker": "B",
        "text": "It's nice, but the living space is a bit small."
      }
    ]
  },
  {
    "phrase": "spruce up",
    "meaning_vi": "làm cho đẹp hơn, tô điểm",
    "type": "phrasal_verb",
    "examples": [
      {
        "en": "I want to spruce up the living room with some new cushions.",
        "vi": "Tôi muốn làm đẹp phòng khách với vài cái gối mới."
      },
      {
        "en": "They spruced up the garden before the party.",
        "vi": "Họ tô điểm khu vườn trước bữa tiệc."
      }
    ],
    "collocations": [
      "spruce up a room",
      "spruce up the house",
      "spruce up with paint"
    ],
    "response": "",
    "example_dialogue": [
      {
        "speaker": "A",
        "text": "The house looks great. Did you spruce it up?"
      },
      {
        "speaker": "B",
        "text": "Yes, we painted the walls and added some plants."
      }
    ]
  },
  {
    "phrase": "nest egg",
    "meaning_vi": "tiền tiết kiệm (dành cho tương lai)",
    "type": "expression",
    "examples": [
      {
        "en": "They have a nest egg for their retirement.",
        "vi": "Họ có một khoản tiết kiệm cho việc nghỉ hưu."
      },
      {
        "en": "We're building a nest egg to buy a house.",
        "vi": "Chúng tôi đang tích lũy tiền để mua nhà."
      }
    ],
    "collocations": [
      "build a nest egg",
      "nest egg savings",
      "retirement nest egg"
    ],
    "response": "",
    "example_dialogue": [
      {
        "speaker": "A",
        "text": "Are you saving for a house?"
      },
      {
        "speaker": "B",
        "text": "Yes, we're trying to build a nest egg."
      }
    ]
  },
  {
    "phrase": "home sweet home",
    "meaning_vi": "nhà là nơi ấm cúng (câu nói khi về nhà)",
    "type": "expression",
    "examples": [
      {
        "en": "After a long trip, it's home sweet home.",
        "vi": "Sau một chuyến đi dài, nhà mới là nơi ấm cúng."
      },
      {
        "en": "She sighed, 'Home sweet home.'",
        "vi": "Cô ấy thở dài, 'Nhà là nơi ấm cúng.'"
      }
    ],
    "collocations": [
      "say home sweet home",
      "feel home sweet home"
    ],
    "response": "Home sweet home!",
    "example_dialogue": [
      {
        "speaker": "A",
        "text": "We're finally back."
      },
      {
        "speaker": "B",
        "text": "Home sweet home!"
      }
    ]
  },
  {
    "phrase": "fix up",
    "meaning_vi": "sửa chữa, sửa sang",
    "type": "phrasal_verb",
    "examples": [
      {
        "en": "We need to fix up the roof before winter.",
        "vi": "Chúng tôi cần sửa mái nhà trước mùa đông."
      },
      {
        "en": "He fixed up the old bike and gave it to his son.",
        "vi": "Anh ấy sửa lại chiếc xe đạp cũ và tặng cho con trai."
      }
    ],
    "collocations": [
      "fix up a house",
      "fix up a room",
      "fix up with furniture"
    ],
    "response": "",
    "example_dialogue": [
      {
        "speaker": "A",
        "text": "Are you going to fix up the spare room?"
      },
      {
        "speaker": "B",
        "text": "Yes, I want to turn it into a home office."
      }
    ]
  }
]